xskillscore/__init__.py
xskillscore/_version.py
xskillscore/core/__init__.py
xskillscore/core/accessor.py
xskillscore/core/comparative.py
xskillscore/core/contingency.py
xskillscore/core/deterministic.py
xskillscore/core/np_deterministic.py
xskillscore/core/np_probabilistic.py
xskillscore/core/probabilistic.py
xskillscore/core/resampling.py
xskillscore/core/stattests.py
xskillscore/core/types.py
xskillscore/core/utils.py
xskillscore/tests/__init__.py
xskillscore/tests/test_accessor_deterministic.py
xskillscore/tests/test_accessor_probabilistic.py
xskillscore/tests/test_comparative.py
xskillscore/tests/test_contingency.py
xskillscore/tests/test_deterministic.py
xskillscore/tests/test_effective_p_value.py
xskillscore/tests/test_gridded_metrics.py
xskillscore/tests/test_mask_skipna.py
xskillscore/tests/test_metric_results_accurate.py
xskillscore/tests/test_probabilistic.py
xskillscore/tests/test_resampling.py
xskillscore/tests/test_skipna_functionality.py
xskillscore/tests/test_stattests.py
xskillscore/tests/test_weighted_metric_results_accurate.py
xskillscore/versioning/__init__.py
xskillscore/versioning/print_versions.py
xskillscore-0.0.28.dist-info/licenses/LICENSE.txt
xskillscore-0.0.28.dist-info/METADATA
xskillscore-0.0.28.dist-info/WHEEL
xskillscore-0.0.28.dist-info/top_level.txt
xskillscore-0.0.28.dist-info/RECORD
