Metadata-Version: 2.4
Name: xskillscore
Version: 0.0.28
Summary: Metrics for verifying forecasts
Author-email: Ray Bell <rayjohnbell0@gmail.com>
License:                                  Apache License
Project-URL: repository, https://github.com/xarray-contrib/xskillscore
Project-URL: documentation, https://xskillscore.readthedocs.io/en/stable/
Classifier: Development Status :: 5 - Production/Stable
Classifier: Intended Audience :: Science/Research
Classifier: License :: OSI Approved :: Apache Software License
Classifier: Natural Language :: English
Classifier: Operating System :: OS Independent
Classifier: Programming Language :: Python :: 3 :: Only
Classifier: Programming Language :: Python :: 3.9
Classifier: Programming Language :: Python :: 3.10
Classifier: Programming Language :: Python :: 3.11
Classifier: Programming Language :: Python :: 3.12
Classifier: Programming Language :: Python :: 3.13
Classifier: Topic :: Scientific/Engineering :: Atmospheric Science
Classifier: Topic :: Scientific/Engineering :: Mathematics
Requires-Python: >=3.9
License-File: LICENSE.txt
Requires-Dist: dask[array]>=2023.4.0
Requires-Dist: numpy<2.4,>=1.24
Requires-Dist: properscoring
Requires-Dist: scipy>=1.10
Requires-Dist: statsmodels
Requires-Dist: xarray>=2023.4.0
Requires-Dist: xhistogram>=0.3.2
Provides-Extra: accel
Requires-Dist: bottleneck; extra == "accel"
Requires-Dist: numba>=0.57; extra == "accel"
Provides-Extra: test
Requires-Dist: xskillscore[accel]; extra == "test"
Requires-Dist: cftime; extra == "test"
Requires-Dist: matplotlib; extra == "test"
Requires-Dist: packaging; extra == "test"
Requires-Dist: pre-commit; extra == "test"
Requires-Dist: pytest; extra == "test"
Requires-Dist: pytest-cov; extra == "test"
Requires-Dist: pytest-timeout; extra == "test"
Requires-Dist: pytest-xdist; extra == "test"
Requires-Dist: scikit-learn; extra == "test"
Provides-Extra: complete
Requires-Dist: xskillscore[test]; extra == "complete"
Requires-Dist: doc8; extra == "complete"
Requires-Dist: ipykernel; extra == "complete"
Requires-Dist: ipython; extra == "complete"
Requires-Dist: nbsphinx; extra == "complete"
Requires-Dist: nbstripout; extra == "complete"
Requires-Dist: properscoring; extra == "complete"
Requires-Dist: pytest-sugar; extra == "complete"
Requires-Dist: sphinx>=6.0.0; extra == "complete"
Requires-Dist: sphinx-autosummary-accessors; extra == "complete"
Requires-Dist: sphinx-copybutton; extra == "complete"
Requires-Dist: sphinx-rtd-theme>=1.0; extra == "complete"
Dynamic: license-file
